pycuts/__init__.py
pycuts/gradio/__init__.py
pycuts/gradio/core.py
pycuts/gradio/layout.py
pycuts/huggingface/__init__.py
pycuts/huggingface/spaces/__init__.py
pycuts/huggingface/spaces/core.py
pycuts/packages/__init__.py
pycuts/packages/availability.py
pycuts/packages/gradio.py
pycuts/packages/spaces.py
pycuts/packages/torch.py
pycuts/torch/__init__.py
pycuts/torch/core.py
pycuts-2025.5.14.2.dist-info/licenses/LICENSE
pycuts-2025.5.14.2.dist-info/licenses/LICENSE.txt
pycuts-2025.5.14.2.dist-info/METADATA
pycuts-2025.5.14.2.dist-info/WHEEL
pycuts-2025.5.14.2.dist-info/top_level.txt
pycuts-2025.5.14.2.dist-info/RECORD
