Metadata-Version: 2.4
Name: pycuts
Version: 2025.5.14.2
Summary: A lightweight Python utility toolkit
Author: Daniel Ialcin Misser Westergaard
License: MIT License
Project-URL: Homepage, https://github.com/dwancin/pycuts
Project-URL: Repository, https://github.com/dwancin/pycuts
Project-URL: Issues, https://github.com/dwancin/pycuts/issues
Keywords: utilities,torch,gradio,huggingface,developer-tools
Classifier: Development Status :: 3 - Alpha
Classifier: Intended Audience :: Developers
Classifier: License :: OSI Approved :: MIT License
Classifier: Operating System :: OS Independent
Classifier: Programming Language :: Python :: 3
Classifier: Programming Language :: Python :: 3.8
Classifier: Programming Language :: Python :: 3.9
Classifier: Programming Language :: Python :: 3.10
Classifier: Programming Language :: Python :: 3.11
Classifier: Programming Language :: Python :: 3.12
Classifier: Topic :: Software Development :: Libraries
Requires-Python: >=3.8
License-File: LICENSE
License-File: LICENSE.txt
Requires-Dist: torch>=1.10.0
Requires-Dist: gradio>=3.0.0
Requires-Dist: huggingface_hub>=0.14.0
Dynamic: license-file
